gogr_tools/__init__.py
gogr_tools/visualisations.py
gogr_tools-0.0.17.dist-info/LICENSE.txt
gogr_tools-0.0.17.dist-info/METADATA
gogr_tools-0.0.17.dist-info/WHEEL
gogr_tools-0.0.17.dist-info/top_level.txt
gogr_tools-0.0.17.dist-info/RECORD
